testmedium/db.py
testmedium-2.0.0.dist-info/LICENCE.txt
testmedium-2.0.0.dist-info/METADATA
testmedium-2.0.0.dist-info/WHEEL
testmedium-2.0.0.dist-info/top_level.txt
testmedium-2.0.0.dist-info/RECORD
